ims_mcp/__init__.py
ims_mcp/mcp_server.py
mcp_search_demo_test-0.1.1.dist-info/METADATA
mcp_search_demo_test-0.1.1.dist-info/WHEEL
mcp_search_demo_test-0.1.1.dist-info/entry_points.txt
mcp_search_demo_test-0.1.1.dist-info/top_level.txt
mcp_search_demo_test-0.1.1.dist-info/RECORD
