Metadata-Version: 2.4
Name: mcp-search-demo-test
Version: 0.1.1
Summary: MCP demo test
Requires-Python: >=3.12
Requires-Dist: alibabacloud-ice20201109==6.4.2
Requires-Dist: mcp>=1.6.0
Requires-Dist: python-dotenv>=1.1.0
